[
    {
        "id":1,
        "title":"Huawei/华为 Mate 40 RS 保时捷设计5G手机现货新款典藏版 麒麟芯",
        "nprice":11999,
        "oprice":12999,
        "num":622,
        "img":"https://g-search3.alicdn.com/img/bao/uploaded/i4/i2/3102564477/O1CN01mGYL0q1iwVor02JQ4_!!3102564477.jpg_360x360Q90.jpg_.webp"

    },
    {
        "id":2,
        "title":"华为p40pro+陶瓷板Huawei/华为 P40 Pro+官方正品分期免息5G手机",
        "nprice":6549,
        "oprice":7569,
        "num":236,
        "img":"https://g-search3.alicdn.com/img/bao/uploaded/i4/i3/64908603/O1CN01R3yQgt2DQDy21R9Ix_!!64908603-0-lubanu-s.jpg_360x360Q90.jpg_.webp"

    },
    {
        "id":3,
        "title":"Canon/佳能PowerShot G7X Mark II 数码相机mark2 g7x2卡片机g7X3",
        "nprice":1800,
        "oprice":2199,
        "num":218,
        "img":"https://g-search2.alicdn.com/img/bao/uploaded/i4/i2/3173948070/O1CN01wBQAf729U6tBxk1ZU_!!3173948070.jpg_580x580Q90.jpg_.webp"

    },
    {
        "id":4,
        "title":"国行联保Canon/佳能PowerShot SX620 HS长焦数码相机高清旅游家用",
        "nprice":1379,
        "oprice":1499,
        "num":218,
        "img":"https://g-search2.alicdn.com/img/bao/uploaded/i4/i1/3200918378/O1CN01S3oQVk2BlAs4XI3YD_!!3200918378.jpg_580x580Q90.jpg_.webp"

    },
    {
        "id":5,
        "title":"当天发货+送小米耳机 xiaomi/小米10手机5g骁龙865全网通小米官方正品旗舰店K30S全新十国风10pro至尊纪念",
        "nprice":3379,
        "oprice":3499,
        "num":218,
        "img":"https://g-search3.alicdn.com/img/bao/uploaded/i4/i2/263726286/O1CN01DzTIwS1wJ2JLlCGC8_!!0-item_pic.jpg_580x580Q90.jpg_.webp"

    },
    {
        "id":6,
        "title":"当天发货+送小米耳机 xiaomi/小米10手机5g骁龙865全网通小米官方正品旗舰店K30S全新十国风10pro至尊纪念",
        "nprice":3379,
        "oprice":3499,
        "num":218,
        "img":"https://g-search3.alicdn.com/img/bao/uploaded/i4/i2/263726286/O1CN01DzTIwS1wJ2JLlCGC8_!!0-item_pic.jpg_580x580Q90.jpg_.webp"

    },
    {
        "id":7,
        "title":"当天发货+送小米耳机 xiaomi/小米10手机5g骁龙865全网通小米官方正品旗舰店K30S全新十国风10pro至尊纪念",
        "nprice":3379,
        "oprice":3499,
        "num":218,
        "img":"https://g-search3.alicdn.com/img/bao/uploaded/i4/i2/263726286/O1CN01DzTIwS1wJ2JLlCGC8_!!0-item_pic.jpg_580x580Q90.jpg_.webp"

    },
    {
        "id":8,
        "title":"当天发货+送小米耳机 xiaomi/小米10手机5g骁龙865全网通小米官方正品旗舰店K30S全新十国风10pro至尊纪念",
        "nprice":3379,
        "oprice":3499,
        "num":218,
        "img":"https://g-search3.alicdn.com/img/bao/uploaded/i4/i2/263726286/O1CN01DzTIwS1wJ2JLlCGC8_!!0-item_pic.jpg_580x580Q90.jpg_.webp"

    },
    {
        "id":9,
        "title":"当天发货+送小米耳机 xiaomi/小米10手机5g骁龙865全网通小米官方正品旗舰店K30S全新十国风10pro至尊纪念",
        "nprice":3379,
        "oprice":3499,
        "num":218,
        "img":"https://g-search3.alicdn.com/img/bao/uploaded/i4/i2/263726286/O1CN01DzTIwS1wJ2JLlCGC8_!!0-item_pic.jpg_580x580Q90.jpg_.webp"

    },
    {
        "id":10,
        "title":"当天发货+送小米耳机 xiaomi/小米10手机5g骁龙865全网通小米官方正品旗舰店K30S全新十国风10pro至尊纪念",
        "nprice":3379,
        "oprice":3499,
        "num":218,
        "img":"https://g-search3.alicdn.com/img/bao/uploaded/i4/i2/263726286/O1CN01DzTIwS1wJ2JLlCGC8_!!0-item_pic.jpg_580x580Q90.jpg_.webp"

    }
]